{"sha": "e535ced2cd22", "date": "1994-03-01", "message": "LOI no 94-89 du 1er février 1994 instituant une peine incompressible et relative au nouveau code pénal et à certaines dispositions de procédure pénale", "files": [{"filename": "chapitre_i/section_i/paragraphe_i/README.md", "articleName": "Sommaire - Paragraphe I", "additions": 0, "deletions": 3, "diff": [{"type": "unchanged", "content": "index 3a34c0f..a3b698a 100644"}, {"type": "unchanged", "content": "--- a/chapitre_i/section_i/paragraphe_i/README.md"}, {"type": "unchanged", "content": "+++ b/chapitre_i/section_i/paragraphe_i/README.md"}, {"type": "unchanged", "content": "- [Article 1](article_1.md)"}, {"type": "unchanged", "content": "- [Article 2](article_2.md)"}, {"type": "unchanged", "content": "- [Article 3](article_3.md)"}, {"type": "del", "content": "- [Article 5](article_5.md)"}, {"type": "del", "content": "- [Article 6](article_6.md)"}, {"type": "del", "content": "- [Article 7](article_7.md)"}, {"type": "unchanged", "content": "- [Article 8](article_8.md)"}, {"type": "unchanged", "content": ""}, {"type": "unchanged", "content": ""}], "status": "modified"}, {"filename": "chapitre_i/section_i/paragraphe_i/article_5.md", "articleName": "Article 5", "additions": 0, "deletions": 78, "diff": [{"type": "unchanged", "content": "deleted file mode 100644"}, {"type": "unchanged", "content": "index f43af59..0000000"}, {"type": "unchanged", "content": "--- a/chapitre_i/section_i/paragraphe_i/article_5.md"}, {"type": "unchanged", "content": "+++ /dev/null"}, {"type": "unchanged", "content": "----"}, {"type": "unchanged", "content": "----"}, {"type": "del", "content": ""}, {"type": "del", "content": "# Article 5"}, {"type": "del", "content": ""}, {"type": "del", "content": "Il est interdit d'employer ou de détenir, à moins d'y avoir été préalablement autorisé, des machines, appareils ou instruments susceptibles d'être utilisés dans la fabrication des monnaies."}, {"type": "del", "content": ""}, {"type": "del", "content": "Les autorisations sont délivrées à Paris par le préfet de police, dans les départements par le préfet pour l'arrondissement chef-lieu, et par les sous-préfets pour les autres arrondissements. Il est interdit de livrer, à quelque titre que ce soit, à des personnes non pourvues de l'autorisation prévue aux alinéas précédents, lesdites machines, appareils ou instruments."}, {"type": "del", "content": ""}, {"type": "del", "content": ""}, {"type": "del", "content": ""}, {"type": "del", "content": "Références"}, {"type": "del", "content": ""}, {"type": "del", "content": "  ### Articles faisant référence à l'article"}, {"type": "del", "content": "  "}, {"type": "del", "content": ""}, {"type": "del", "content": ""}, {"type": "del", "content": "Code des instruments monétaires et des médailles - article 6 AUTONOME ABROGE, en vigueur du 1952-06-29 au 1994-03-01 CITATION source"}, {"type": "del", "content": ""}, {"type": "del", "content": ""}, {"type": "del", "content": "Code des instruments monétaires et des médailles - article 7 AUTONOME MODIFIE_MORT_NE, en vigueur du 1994-03-01 au 1994-02-02 CITATION source"}, {"type": "del", "content": ""}, {"type": "del", "content": ""}, {"type": "del", "content": "Loi n° 94-89 du 1 février 1994 instituant une peine incompressible et relative au nouveau code pénal et à certaines dispositions de procédure pénale - article 14 AUTONOME VIGUEUR, en vigueur depuis le 1994-03-01 ABROGATION cible"}, {"type": "del", "content": ""}, {"type": "del", "content": ""}, {"type": "del", "content": "Loi n° 94-89 du 1 février 1994 instituant une peine incompressible et relative au nouveau code pénal et à certaines dispositions de procédure pénale - article 14 AUTONOME VIGUEUR, en vigueur depuis le 1994-03-01 CITATION source"}, {"type": "del", "content": ""}, {"type": "del", "content": ""}, {"type": "del", "content": "Code des instruments monétaires et des médailles - article 7 AUTONOME MODIFIE, en vigueur du 1952-06-29 au 1994-03-01 CITATION source"}, {"type": "del", "content": ""}, {"type": "del", "content": ""}, {"type": "del", "content": "  "}, {"type": "del", "content": "  ### Textes faisant référence à l'article"}, {"type": "del", "content": "  "}, {"type": "del", "content": ""}, {"type": "del", "content": ""}, {"type": "del", "content": "LOI n° 58-346 du 3 avril 1958 relative aux conditions d'application de certaines codes CODIFICATION cible"}, {"type": "del", "content": ""}, {"type": "del", "content": ""}, {"type": "del", "content": "  "}, {"type": "del", "content": "  ### Références faites par l'article"}, {"type": "del", "content": "  "}, {"type": "del", "content": ""}, {"type": "del", "content": ""}, {"type": "del", "content": "1958-04-03 CODIFICATION source LOI n° 58-346 du 3 avril 1958 relative aux conditions d'application de certaines codes"}, {"type": "del", "content": ""}, {"type": "del", "content": ""}, {"type": "del", "content": "1994-02-01 ABROGATION source Loi n° 94-89 du 1 février 1994 instituant une peine incompressible et relative au nouveau code pénal et à certaines dispositions de procédure pénale - article 14 AUTONOME VIGUEUR, en vigueur depuis le 1994-03-01"}, {"type": "del", "content": ""}, {"type": "del", "content": ""}, {"type": "del", "content": "1994-02-01 CITATION cible Loi n° 94-89 du 1 février 1994 instituant une peine incompressible et relative au nouveau code pénal et à certaines dispositions de procédure pénale - article 14 AUTONOME VIGUEUR, en vigueur depuis le 1994-03-01"}, {"type": "del", "content": ""}, {"type": "del", "content": ""}, {"type": "del", "content": "2999-01-01 CITATION cible Code des instruments monétaires et des médailles - article 6 AUTONOME ABROGE, en vigueur du 1952-06-29 au 1994-03-01"}, {"type": "del", "content": ""}, {"type": "del", "content": ""}, {"type": "del", "content": "2999-01-01 CITATION cible Code des instruments monétaires et des médailles - article 7 AUTONOME MODIFIE_MORT_NE, en vigueur du 1994-03-01 au 1994-02-02"}, {"type": "del", "content": ""}, {"type": "del", "content": ""}, {"type": "del", "content": "2999-01-01 TXT_ASSOCIE source Code des instruments monétaires et des médailles VIGUEUR"}, {"type": "del", "content": ""}, {"type": "del", "content": ""}, {"type": "del", "content": "      CODIFICATION source Décret 52-751 1952-06-26"}, {"type": "del", "content": ""}, {"type": "del", "content": ""}, {"type": "del", "content": "      CREATION source Décret 52-751 1952-06-26 JORF 29 juin 1952 rectificatif JORF 10 juillet 1952"}, {"type": "del", "content": ""}, {"type": "del", "content": ""}, {"type": "del", "content": ""}, {"type": "del", "content": ""}, {"type": "del", "content": ""}, {"type": "del", "content": "Autres formats"}, {"type": "del", "content": ""}, {"type": "del", "content": "* [JSON dans git](https://git.tricoteuses.fr/dila/donnees_juridiques/src/branch/main/LEGI/ARTI/00/00/06/39/81/LEGIARTI000006398138.json)"}, {"type": "del", "content": "* [Références JSON dans git](https://git.tricoteuses.fr/dila/references_donnees_juridiques/src/branch/main/LEGI/ARTI/00/00/06/39/81/LEGIARTI000006398138.json)"}, {"type": "del", "content": "* [Markdown dans git](https://git.tricoteuses.fr/dila/textes_juridiques/src/branch/main/LEGI/ARTI/00/00/06/39/81/LEGIARTI000006398138.md)"}, {"type": "del", "content": "* [Markdown chronologique dans git](https://git.tricoteuses.fr/codes/code_des_instruments_monetaires_et_des_medailles/src/branch/main/chapitre_i/section_i/paragraphe_i/article_5.md)"}, {"type": "del", "content": "* [Légifrance](https://www.legifrance.gouv.fr/codes/article_lc/LEGIARTI000006398138)"}, {"type": "del", "content": ""}], "status": "deleted"}, {"filename": "chapitre_i/section_i/paragraphe_i/article_6.md", "articleName": "Article 6", "additions": 0, "deletions": 79, "diff": [{"type": "unchanged", "content": "deleted file mode 100644"}, {"type": "unchanged", "content": "index a6ec0fc..0000000"}, {"type": "unchanged", "content": "--- a/chapitre_i/section_i/paragraphe_i/article_6.md"}, {"type": "unchanged", "content": "+++ /dev/null"}, {"type": "unchanged", "content": "----"}, {"type": "unchanged", "content": "----"}, {"type": "del", "content": ""}, {"type": "del", "content": "# Article 6"}, {"type": "del", "content": ""}, {"type": "del", "content": "Les machines, appareils et instruments auxquels sont applicables les interdictions portées par l'article 5 sont désignés par des décrets. Ceux-ci règlent les formes et conditions des autorisations qui y sont prévues et déterminent toutes les mesures d'exécution des articles 5 et 6."}, {"type": "del", "content": ""}, {"type": "del", "content": ""}, {"type": "del", "content": ""}, {"type": "del", "content": "Références"}, {"type": "del", "content": ""}, {"type": "del", "content": "  ### Articles faisant référence à l'article"}, {"type": "del", "content": "  "}, {"type": "del", "content": ""}, {"type": "del", "content": ""}, {"type": "del", "content": "Code des instruments monétaires et des médailles - article 5 AUTONOME ABROGE, en vigueur du 1952-06-29 au 1994-03-01 CITATION cible"}, {"type": "del", "content": ""}, {"type": "del", "content": ""}, {"type": "del", "content": "Code des instruments monétaires et des médailles - article 6 AUTONOME ABROGE, en vigueur du 1952-06-29 au 1994-03-01 CITATION cible"}, {"type": "del", "content": ""}, {"type": "del", "content": ""}, {"type": "del", "content": "Code des instruments monétaires et des médailles - article 7 AUTONOME MODIFIE_MORT_NE, en vigueur du 1994-03-01 au 1994-02-02 CITATION source"}, {"type": "del", "content": ""}, {"type": "del", "content": ""}, {"type": "del", "content": "Loi n° 94-89 du 1 février 1994 instituant une peine incompressible et relative au nouveau code pénal et à certaines dispositions de procédure pénale - article 14 AUTONOME VIGUEUR, en vigueur depuis le 1994-03-01 ABROGATION cible"}, {"type": "del", "content": ""}, {"type": "del", "content": ""}, {"type": "del", "content": "Loi n° 94-89 du 1 février 1994 instituant une peine incompressible et relative au nouveau code pénal et à certaines dispositions de procédure pénale - article 14 AUTONOME VIGUEUR, en vigueur depuis le 1994-03-01 CITATION source"}, {"type": "del", "content": ""}, {"type": "del", "content": ""}, {"type": "del", "content": "Code des instruments monétaires et des médailles - article 7 AUTONOME MODIFIE, en vigueur du 1952-06-29 au 1994-03-01 CITATION source"}, {"type": "del", "content": ""}, {"type": "del", "content": ""}, {"type": "del", "content": "  "}, {"type": "del", "content": "  ### Textes faisant référence à l'article"}, {"type": "del", "content": "  "}, {"type": "del", "content": ""}, {"type": "del", "content": ""}, {"type": "del", "content": "LOI n° 58-346 du 3 avril 1958 relative aux conditions d'application de certaines codes CODIFICATION cible"}, {"type": "del", "content": ""}, {"type": "del", "content": ""}, {"type": "del", "content": "  "}, {"type": "del", "content": "  ### Références faites par l'article"}, {"type": "del", "content": "  "}, {"type": "del", "content": ""}, {"type": "del", "content": ""}, {"type": "del", "content": "      CODIFICATION source Décret 52-751 1952-06-26"}, {"type": "del", "content": ""}, {"type": "del", "content": ""}, {"type": "del", "content": "      CREATION source Décret 52-751 1952-06-26 JORF 29 juin 1952 rectificatif JORF 10 juillet 1952"}, {"type": "del", "content": ""}, {"type": "del", "content": ""}, {"type": "del", "content": "1958-04-03 CODIFICATION source LOI n° 58-346 du 3 avril 1958 relative aux conditions d'application de certaines codes"}, {"type": "del", "content": ""}, {"type": "del", "content": ""}, {"type": "del", "content": "1994-02-01 ABROGATION source Loi n° 94-89 du 1 février 1994 instituant une peine incompressible et relative au nouveau code pénal et à certaines dispositions de procédure pénale - article 14 AUTONOME VIGUEUR, en vigueur depuis le 1994-03-01"}, {"type": "del", "content": ""}, {"type": "del", "content": ""}, {"type": "del", "content": "1994-02-01 CITATION cible Loi n° 94-89 du 1 février 1994 instituant une peine incompressible et relative au nouveau code pénal et à certaines dispositions de procédure pénale - article 14 AUTONOME VIGUEUR, en vigueur depuis le 1994-03-01"}, {"type": "del", "content": ""}, {"type": "del", "content": ""}, {"type": "del", "content": "2999-01-01 CITATION source Code des instruments monétaires et des médailles - article 5 AUTONOME ABROGE, en vigueur du 1952-06-29 au 1994-03-01"}, {"type": "del", "content": ""}, {"type": "del", "content": ""}, {"type": "del", "content": "2999-01-01 CITATION cible Code des instruments monétaires et des médailles - article 6 AUTONOME ABROGE, en vigueur du 1952-06-29 au 1994-03-01"}, {"type": "del", "content": ""}, {"type": "del", "content": ""}, {"type": "del", "content": "2999-01-01 CITATION cible Code des instruments monétaires et des médailles - article 7 AUTONOME MODIFIE_MORT_NE, en vigueur du 1994-03-01 au 1994-02-02"}, {"type": "del", "content": ""}, {"type": "del", "content": ""}, {"type": "del", "content": ""}, {"type": "del", "content": ""}, {"type": "del", "content": ""}, {"type": "del", "content": "Autres formats"}, {"type": "del", "content": ""}, {"type": "del", "content": "* [JSON dans git](https://git.tricoteuses.fr/dila/donnees_juridiques/src/branch/main/LEGI/ARTI/00/00/06/39/81/LEGIARTI000006398147.json)"}, {"type": "del", "content": "* [Références JSON dans git](https://git.tricoteuses.fr/dila/references_donnees_juridiques/src/branch/main/LEGI/ARTI/00/00/06/39/81/LEGIARTI000006398147.json)"}, {"type": "del", "content": "* [Markdown dans git](https://git.tricoteuses.fr/dila/textes_juridiques/src/branch/main/LEGI/ARTI/00/00/06/39/81/LEGIARTI000006398147.md)"}, {"type": "del", "content": "* [Markdown chronologique dans git](https://git.tricoteuses.fr/codes/code_des_instruments_monetaires_et_des_medailles/src/branch/main/chapitre_i/section_i/paragraphe_i/article_6.md)"}, {"type": "del", "content": "* [Légifrance](https://www.legifrance.gouv.fr/codes/article_lc/LEGIARTI000006398147)"}, {"type": "del", "content": ""}], "status": "deleted"}, {"filename": "chapitre_i/section_i/paragraphe_i/article_7.md", "articleName": "Article 7", "additions": 0, "deletions": 60, "diff": [{"type": "unchanged", "content": "deleted file mode 100644"}, {"type": "unchanged", "content": "index cbf4309..0000000"}, {"type": "unchanged", "content": "--- a/chapitre_i/section_i/paragraphe_i/article_7.md"}, {"type": "unchanged", "content": "+++ /dev/null"}, {"type": "unchanged", "content": "----"}, {"type": "unchanged", "content": "----"}, {"type": "del", "content": ""}, {"type": "del", "content": "# Article 7"}, {"type": "del", "content": ""}, {"type": "del", "content": "Toute infraction aux dispositions des articles 5 et 6 ou du décret, rendu pour leur exécution, sera punie d'une amende de 60 à 15.000 F et de la confiscation des machines, appareils ou instruments employés, détenus ou livrés irrégulièrement."}, {"type": "del", "content": ""}, {"type": "del", "content": "En cas de récidive, l'amende sera de 1.800 à 16.000 F."}, {"type": "del", "content": ""}, {"type": "del", "content": ""}, {"type": "del", "content": ""}, {"type": "del", "content": "Références"}, {"type": "del", "content": ""}, {"type": "del", "content": "  ### Articles faisant référence à l'article"}, {"type": "del", "content": "  "}, {"type": "del", "content": ""}, {"type": "del", "content": ""}, {"type": "del", "content": "Loi n° 94-89 du 1 février 1994 instituant une peine incompressible et relative au nouveau code pénal et à certaines dispositions de procédure pénale - article 14 AUTONOME VIGUEUR, en vigueur depuis le 1994-03-01 CITATION source"}, {"type": "del", "content": ""}, {"type": "del", "content": ""}, {"type": "del", "content": "  "}, {"type": "del", "content": "  ### Textes faisant référence à l'article"}, {"type": "del", "content": "  "}, {"type": "del", "content": ""}, {"type": "del", "content": ""}, {"type": "del", "content": "LOI n° 58-346 du 3 avril 1958 relative aux conditions d'application de certaines codes CODIFICATION cible"}, {"type": "del", "content": ""}, {"type": "del", "content": ""}, {"type": "del", "content": "  "}, {"type": "del", "content": "  ### Références faites par l'article"}, {"type": "del", "content": "  "}, {"type": "del", "content": ""}, {"type": "del", "content": ""}, {"type": "del", "content": "1958-04-03 CODIFICATION source LOI n° 58-346 du 3 avril 1958 relative aux conditions d'application de certaines codes"}, {"type": "del", "content": ""}, {"type": "del", "content": ""}, {"type": "del", "content": "1994-02-01 CITATION cible Loi n° 94-89 du 1 février 1994 instituant une peine incompressible et relative au nouveau code pénal et à certaines dispositions de procédure pénale - article 14 AUTONOME VIGUEUR, en vigueur depuis le 1994-03-01"}, {"type": "del", "content": ""}, {"type": "del", "content": ""}, {"type": "del", "content": "2999-01-01 CITATION source Code des instruments monétaires et des médailles - article 5 AUTONOME ABROGE, en vigueur du 1952-06-29 au 1994-03-01"}, {"type": "del", "content": ""}, {"type": "del", "content": ""}, {"type": "del", "content": "2999-01-01 CITATION source Code des instruments monétaires et des médailles - article 6 AUTONOME ABROGE, en vigueur du 1952-06-29 au 1994-03-01"}, {"type": "del", "content": ""}, {"type": "del", "content": ""}, {"type": "del", "content": "      CODIFICATION source Décret 52-751 1952-06-26"}, {"type": "del", "content": ""}, {"type": "del", "content": ""}, {"type": "del", "content": "      CREATION source Décret 52-751 1952-06-26 JORF 29 juin 1952 rectificatif JORF 10 juillet 1952"}, {"type": "del", "content": ""}, {"type": "del", "content": ""}, {"type": "del", "content": ""}, {"type": "del", "content": ""}, {"type": "del", "content": ""}, {"type": "del", "content": "Autres formats"}, {"type": "del", "content": ""}, {"type": "del", "content": "* [JSON dans git](https://git.tricoteuses.fr/dila/donnees_juridiques/src/branch/main/LEGI/ARTI/00/00/06/39/81/LEGIARTI000006398156.json)"}, {"type": "del", "content": "* [Références JSON dans git](https://git.tricoteuses.fr/dila/references_donnees_juridiques/src/branch/main/LEGI/ARTI/00/00/06/39/81/LEGIARTI000006398156.json)"}, {"type": "del", "content": "* [Markdown dans git](https://git.tricoteuses.fr/dila/textes_juridiques/src/branch/main/LEGI/ARTI/00/00/06/39/81/LEGIARTI000006398156.md)"}, {"type": "del", "content": "* [Markdown chronologique dans git](https://git.tricoteuses.fr/codes/code_des_instruments_monetaires_et_des_medailles/src/branch/main/chapitre_i/section_i/paragraphe_i/article_7.md)"}, {"type": "del", "content": "* [Légifrance](https://www.legifrance.gouv.fr/codes/article_lc/LEGIARTI000006398156)"}, {"type": "del", "content": ""}], "status": "deleted"}], "stats": {"additions": 0, "deletions": 220, "filesChanged": 4}}