{"sha":"c0d1ed007459","date":"2017-01-01","message":"Décret n° 2016-1922 du 28 décembre 2016 relatif à la publication en ligne des documents administratifs","files":[{"filename":"livre_iii/titre_ier/chapitre_ii/section_1/README.md","articleName":"Sommaire - Section 1","additions":2,"deletions":0,"diff":[{"type":"add","content":"- [Article D312-1-1-1](article_d312-1-1-1.md)"},{"type":"add","content":"- [Article D312-1-4](article_d312-1-4.md)"}],"status":"modified"},{"filename":"livre_iii/titre_ier/chapitre_ii/section_1/article_d312-1-1-1.md","articleName":"Article D312-1-1-1","additions":52,"deletions":0,"diff":[{"type":"add","content":"---"},{"type":"add","content":"---"},{"type":"add","content":""},{"type":"add","content":"# Article D312-1-1-1"},{"type":"add","content":""},{"type":"add","content":"Le seuil prévu à l'article L. 312-1-1 est fixé à 50 agents ou salariés exprimé en équivalents temps plein."},{"type":"add","content":""},{"type":"add","content":""},{"type":"add","content":""},{"type":"add","content":"Références"},{"type":"add","content":""},{"type":"add","content":"  ### Articles faisant référence à l'article"},{"type":"add","content":"  "},{"type":"add","content":""},{"type":"add","content":""},{"type":"add","content":"Code des relations entre le public et l'administration - article L312-1-1 AUTONOME VIGUEUR, en vigueur depuis le 2016-10-09 CITATION cible"},{"type":"add","content":""},{"type":"add","content":""},{"type":"add","content":"Décret n° 2016-1922 du 28 décembre 2016 relatif à la publication en ligne des documents administratifs - article 1 ENTIEREMENT_MODIF CREE source"},{"type":"add","content":""},{"type":"add","content":""},{"type":"add","content":"  "},{"type":"add","content":"  ### Références faites par l'article"},{"type":"add","content":"  "},{"type":"add","content":""},{"type":"add","content":""},{"type":"add","content":"2016-12-28 CREE cible Décret n° 2016-1922 du 28 décembre 2016 relatif à la publication en ligne des documents administratifs - article 1 ENTIEREMENT_MODIF"},{"type":"add","content":""},{"type":"add","content":""},{"type":"add","content":"2999-01-01 CITATION cible Code des relations entre le public et l'administration - article D552-11 AUTONOME VIGUEUR, en vigueur depuis le 2021-12-04"},{"type":"add","content":""},{"type":"add","content":""},{"type":"add","content":"2999-01-01 CITATION cible Code des relations entre le public et l'administration - article D562-11 AUTONOME VIGUEUR, en vigueur depuis le 2021-12-04"},{"type":"add","content":""},{"type":"add","content":""},{"type":"add","content":"2999-01-01 CITATION cible Code des relations entre le public et l'administration - article D574-4 AUTONOME VIGUEUR, en vigueur depuis le 2021-12-04"},{"type":"add","content":""},{"type":"add","content":""},{"type":"add","content":"2999-01-01 CITATION source Code des relations entre le public et l'administration - article L312-1-1 AUTONOME VIGUEUR, en vigueur depuis le 2016-10-09"},{"type":"add","content":""},{"type":"add","content":""},{"type":"add","content":""},{"type":"add","content":""},{"type":"add","content":""},{"type":"add","content":"Autres formats"},{"type":"add","content":""},{"type":"add","content":"* [JSON dans git](https://git.tricoteuses.fr/dila/donnees_juridiques/src/branch/main/LEGI/ARTI/00/00/33/74/00/LEGIARTI000033740095.json)"},{"type":"add","content":"* [Références JSON dans git](https://git.tricoteuses.fr/dila/references_donnees_juridiques/src/branch/main/LEGI/ARTI/00/00/33/74/00/LEGIARTI000033740095.json)"},{"type":"add","content":"* [Markdown dans git](https://git.tricoteuses.fr/dila/textes_juridiques/src/branch/main/LEGI/ARTI/00/00/33/74/00/LEGIARTI000033740095.md)"},{"type":"add","content":"* [Markdown chronologique dans git](https://git.tricoteuses.fr/codes/code_des_relations_entre_le_public_et_l_administration/src/branch/main/livre_iii/titre_ier/chapitre_ii/section_1/article_d312-1-1-1.md)"},{"type":"add","content":"* [Légifrance](https://www.legifrance.gouv.fr/codes/article_lc/LEGIARTI000033740095)"},{"type":"add","content":""}],"status":"added"},{"filename":"livre_iii/titre_ier/chapitre_ii/section_1/article_d312-1-4.md","articleName":"Article D312-1-4","additions":52,"deletions":0,"diff":[{"type":"add","content":"---"},{"type":"add","content":"---"},{"type":"add","content":""},{"type":"add","content":"# Article D312-1-4"},{"type":"add","content":""},{"type":"add","content":"Le seuil prévu à l'article L. 312-1-3 est fixé à 50 agents ou salariés exprimé en équivalents temps plein."},{"type":"add","content":""},{"type":"add","content":""},{"type":"add","content":""},{"type":"add","content":"Références"},{"type":"add","content":""},{"type":"add","content":"  ### Articles faisant référence à l'article"},{"type":"add","content":"  "},{"type":"add","content":""},{"type":"add","content":""},{"type":"add","content":"Code des relations entre le public et l'administration - article L312-1-3 AUTONOME VIGUEUR, en vigueur depuis le 2016-10-09 CITATION cible"},{"type":"add","content":""},{"type":"add","content":""},{"type":"add","content":"Décret n° 2016-1922 du 28 décembre 2016 relatif à la publication en ligne des documents administratifs - article 1 ENTIEREMENT_MODIF CREE source"},{"type":"add","content":""},{"type":"add","content":""},{"type":"add","content":"  "},{"type":"add","content":"  ### Références faites par l'article"},{"type":"add","content":"  "},{"type":"add","content":""},{"type":"add","content":""},{"type":"add","content":"2016-12-28 CREE cible Décret n° 2016-1922 du 28 décembre 2016 relatif à la publication en ligne des documents administratifs - article 1 ENTIEREMENT_MODIF"},{"type":"add","content":""},{"type":"add","content":""},{"type":"add","content":"2999-01-01 CITATION cible Code des relations entre le public et l'administration - article D552-11 AUTONOME VIGUEUR, en vigueur depuis le 2021-12-04"},{"type":"add","content":""},{"type":"add","content":""},{"type":"add","content":"2999-01-01 CITATION cible Code des relations entre le public et l'administration - article D562-11 AUTONOME VIGUEUR, en vigueur depuis le 2021-12-04"},{"type":"add","content":""},{"type":"add","content":""},{"type":"add","content":"2999-01-01 CITATION cible Code des relations entre le public et l'administration - article D574-4 AUTONOME VIGUEUR, en vigueur depuis le 2021-12-04"},{"type":"add","content":""},{"type":"add","content":""},{"type":"add","content":"2999-01-01 CITATION source Code des relations entre le public et l'administration - article L312-1-3 AUTONOME VIGUEUR, en vigueur depuis le 2016-10-09"},{"type":"add","content":""},{"type":"add","content":""},{"type":"add","content":""},{"type":"add","content":""},{"type":"add","content":""},{"type":"add","content":"Autres formats"},{"type":"add","content":""},{"type":"add","content":"* [JSON dans git](https://git.tricoteuses.fr/dila/donnees_juridiques/src/branch/main/LEGI/ARTI/00/00/33/74/01/LEGIARTI000033740114.json)"},{"type":"add","content":"* [Références JSON dans git](https://git.tricoteuses.fr/dila/references_donnees_juridiques/src/branch/main/LEGI/ARTI/00/00/33/74/01/LEGIARTI000033740114.json)"},{"type":"add","content":"* [Markdown dans git](https://git.tricoteuses.fr/dila/textes_juridiques/src/branch/main/LEGI/ARTI/00/00/33/74/01/LEGIARTI000033740114.md)"},{"type":"add","content":"* [Markdown chronologique dans git](https://git.tricoteuses.fr/codes/code_des_relations_entre_le_public_et_l_administration/src/branch/main/livre_iii/titre_ier/chapitre_ii/section_1/article_d312-1-4.md)"},{"type":"add","content":"* [Légifrance](https://www.legifrance.gouv.fr/codes/article_lc/LEGIARTI000033740114)"},{"type":"add","content":""}],"status":"added"},{"filename":"livre_v/titre_v/chapitre_ii/section_2/sous-section_3/README.md","articleName":"Sommaire - Sous-Section 3","additions":1,"deletions":0,"diff":[{"type":"add","content":"- [Article D552-11](article_d552-11.md)"}],"status":"modified"},{"filename":"livre_v/titre_v/chapitre_ii/section_2/sous-section_3/article_d552-11.md","articleName":"Article D552-11","additions":116,"deletions":0,"diff":[{"type":"add","content":"---"},{"type":"add","content":"---"},{"type":"add","content":""},{"type":"add","content":"# Article D552-11"},{"type":"add","content":""},{"type":"add","content":"Les dispositions du livre III mentionnées dans la colonne de gauche du tableau ci-après sont applicables en Polynésie française aux relations entre le public, d'une part, et les organismes et personnes de droit public et de droit privé, autres que les établissements publics, chargés par l'Etat et les communes d'une mission de service public administratif et, le cas échéant, industriel et commercial, d'autre part, dans leur rédaction indiquée dans la colonne de droite du même tableau."},{"type":"add","content":""},{"type":"add","content":""},{"type":"add","content":""},{"type":"add","content":""},{"type":"add","content":""},{"type":"add","content":""},{"type":"add","content":"DISPOSITIONS APPLICABLES"},{"type":"add","content":""},{"type":"add","content":""},{"type":"add","content":"DANS LEUR RÉDACTION"},{"type":"add","content":""},{"type":"add","content":""},{"type":"add","content":""},{"type":"add","content":""},{"type":"add","content":"D. 312-1-1-1 et D. 312-1-4"},{"type":"add","content":""},{"type":"add","content":""},{"type":"add","content":"Résultant du décret n° 2016-1922"},{"type":"add","content":""},{"type":"add","content":""},{"type":"add","content":""},{"type":"add","content":""},{"type":"add","content":"D. 324-5-1"},{"type":"add","content":""},{"type":"add","content":""},{"type":"add","content":"Résultant du décret n° 2016-1617"},{"type":"add","content":""},{"type":"add","content":""},{"type":"add","content":""},{"type":"add","content":""},{"type":"add","content":"D. 341-10"},{"type":"add","content":""},{"type":"add","content":""},{"type":"add","content":"Résultant du décret n° 2016-308"},{"type":"add","content":""},{"type":"add","content":""},{"type":"add","content":""},{"type":"add","content":""},{"type":"add","content":"D. 341-11 à D. 341-15"},{"type":"add","content":""},{"type":"add","content":""},{"type":"add","content":"Résultant du décret n° 2015-1342"},{"type":"add","content":""},{"type":"add","content":""},{"type":"add","content":""},{"type":"add","content":""},{"type":"add","content":""},{"type":"add","content":""},{"type":"add","content":""},{"type":"add","content":""},{"type":"add","content":"Références"},{"type":"add","content":""},{"type":"add","content":"  ### Articles faisant référence à l'article"},{"type":"add","content":"  "},{"type":"add","content":""},{"type":"add","content":""},{"type":"add","content":"Décret n° 2016-1922 du 28 décembre 2016 relatif à la publication en ligne des documents administratifs - article 2 ENTIEREMENT_MODIF MODIFIE source"},{"type":"add","content":""},{"type":"add","content":""},{"type":"add","content":"  "},{"type":"add","content":"  ### Textes faisant référence à l'article"},{"type":"add","content":"  "},{"type":"add","content":""},{"type":"add","content":""},{"type":"add","content":"Décret n° 2016-308 du 17 mars 2016 relatif à la réutilisation des informations publiques et modifiant le code des relations entre le public et l'administration (dispositions réglementaires) CITATION cible"},{"type":"add","content":""},{"type":"add","content":""},{"type":"add","content":"Décret n° 2016-1617 du 29 novembre 2016 relatif aux catégories d'informations publiques de l'Etat et de ses établissements publics administratifs susceptibles d'être soumises au paiement d'une redevance de réutilisation CITATION cible"},{"type":"add","content":""},{"type":"add","content":""},{"type":"add","content":"Décret n° 2016-1922 du 28 décembre 2016 relatif à la publication en ligne des documents administratifs CITATION cible"},{"type":"add","content":""},{"type":"add","content":""},{"type":"add","content":"Décret n° 2015-1342 du 23 octobre 2015 relatif aux dispositions réglementaires du code des relations entre le public et l'administration (Décrets en Conseil d'Etat et en conseil des ministres, décrets en Conseil d'Etat et décrets) CITATION cible"},{"type":"add","content":""},{"type":"add","content":""},{"type":"add","content":"  "},{"type":"add","content":"  ### Références faites par l'article"},{"type":"add","content":"  "},{"type":"add","content":""},{"type":"add","content":""},{"type":"add","content":"2015-10-23 CITATION source Décret n° 2015-1342 du 23 octobre 2015 relatif aux dispositions réglementaires du code des relations entre le public et l'administration (Décrets en Conseil d'Etat et en conseil des ministres, décrets en Conseil d'Etat et décrets)"},{"type":"add","content":""},{"type":"add","content":""},{"type":"add","content":"CODIFICATION source Décret n° 2015-1342 du 23 octobre 2015 relatif aux dispositions réglementaires du code des relations entre le public et l'administration (Décrets en Conseil d'Etat et en conseil des ministres, décrets en Conseil d'Etat et décrets)"},{"type":"add","content":""},{"type":"add","content":""},{"type":"add","content":"2016-03-17 CITATION source Décret n° 2016-308 du 17 mars 2016 relatif à la réutilisation des informations publiques et modifiant le code des relations entre le public et l'administration (dispositions réglementaires)"},{"type":"add","content":""},{"type":"add","content":""},{"type":"add","content":"2016-11-29 CITATION source Décret n° 2016-1617 du 29 novembre 2016 relatif aux catégories d'informations publiques de l'Etat et de ses établissements publics administratifs susceptibles d'être soumises au paiement d'une redevance de réutilisation"},{"type":"add","content":""},{"type":"add","content":""},{"type":"add","content":"2016-12-28 CITATION source Décret n° 2016-1922 du 28 décembre 2016 relatif à la publication en ligne des documents administratifs"},{"type":"add","content":""},{"type":"add","content":""},{"type":"add","content":"2016-12-28 MODIFIE cible Décret n° 2016-1922 du 28 décembre 2016 relatif à la publication en ligne des documents administratifs - article 2 ENTIEREMENT_MODIF"},{"type":"add","content":""},{"type":"add","content":""},{"type":"add","content":""},{"type":"add","content":""},{"type":"add","content":""},{"type":"add","content":"Autres formats"},{"type":"add","content":""},{"type":"add","content":"* [JSON dans git](https://git.tricoteuses.fr/dila/donnees_juridiques/src/branch/main/LEGI/ARTI/00/00/33/74/81/LEGIARTI000033748153.json)"},{"type":"add","content":"* [Références JSON dans git](https://git.tricoteuses.fr/dila/references_donnees_juridiques/src/branch/main/LEGI/ARTI/00/00/33/74/81/LEGIARTI000033748153.json)"},{"type":"add","content":"* [Markdown dans git](https://git.tricoteuses.fr/dila/textes_juridiques/src/branch/main/LEGI/ARTI/00/00/33/74/81/LEGIARTI000033748153.md)"},{"type":"add","content":"* [Markdown chronologique dans git](https://git.tricoteuses.fr/codes/code_des_relations_entre_le_public_et_l_administration/src/branch/main/livre_v/titre_v/chapitre_ii/section_2/sous-section_3/article_d552-11.md)"},{"type":"add","content":"* [Légifrance](https://www.legifrance.gouv.fr/codes/article_lc/LEGIARTI000033748153)"},{"type":"add","content":""}],"status":"added"},{"filename":"livre_v/titre_vi/chapitre_ii/section_2/sous-section_3/README.md","articleName":"Sommaire - Sous-Section 3","additions":1,"deletions":0,"diff":[{"type":"add","content":"- [Article D562-11](article_d562-11.md)"}],"status":"modified"},{"filename":"livre_v/titre_vi/chapitre_ii/section_2/sous-section_3/article_d562-11.md","articleName":"Article D562-11","additions":125,"deletions":0,"diff":[{"type":"add","content":"---"},{"type":"add","content":"---"},{"type":"add","content":""},{"type":"add","content":"# Article D562-11"},{"type":"add","content":""},{"type":"add","content":"Les dispositions du livre III mentionnées dans la colonne de gauche du tableau ci-après sont applicables en Nouvelle-Calédonie aux relations entre le public, d'une part, et les organismes et personnes de droit public et de droit privé, autres que les établissements publics, chargés par l'Etat et les communes d'une mission de service public administratif et, le cas échéant, industriel et commercial, d'autre part, dans leur rédaction indiquée dans la colonne de droite du même tableau."},{"type":"add","content":""},{"type":"add","content":""},{"type":"add","content":""},{"type":"add","content":""},{"type":"add","content":""},{"type":"add","content":""},{"type":"add","content":"DISPOSITIONS APPLICABLES"},{"type":"add","content":"DANS LEUR RÉDACTION"},{"type":"add","content":""},{"type":"add","content":""},{"type":"add","content":""},{"type":"add","content":"D. 312-1-1-1 et D. 312-1-4"},{"type":"add","content":""},{"type":"add","content":""},{"type":"add","content":"Résultant du décret n° 2016-1922"},{"type":"add","content":""},{"type":"add","content":""},{"type":"add","content":""},{"type":"add","content":""},{"type":"add","content":"D. 324-5-1"},{"type":"add","content":""},{"type":"add","content":""},{"type":"add","content":"Résultant du décret n° 2016-1617"},{"type":"add","content":""},{"type":"add","content":""},{"type":"add","content":""},{"type":"add","content":""},{"type":"add","content":""},{"type":"add","content":""},{"type":"add","content":"D. 341-10"},{"type":"add","content":""},{"type":"add","content":""},{"type":"add","content":""},{"type":"add","content":""},{"type":"add","content":""},{"type":"add","content":"Résultant du décret n° 2016-308"},{"type":"add","content":""},{"type":"add","content":""},{"type":"add","content":""},{"type":"add","content":""},{"type":"add","content":""},{"type":"add","content":""},{"type":"add","content":""},{"type":"add","content":"D. 341-11 à D. 341-15"},{"type":"add","content":""},{"type":"add","content":""},{"type":"add","content":""},{"type":"add","content":""},{"type":"add","content":""},{"type":"add","content":"            Résultant du décret n° 2015-1342"},{"type":"add","content":""},{"type":"add","content":""},{"type":"add","content":""},{"type":"add","content":""},{"type":"add","content":""},{"type":"add","content":""},{"type":"add","content":""},{"type":"add","content":""},{"type":"add","content":""},{"type":"add","content":"Références"},{"type":"add","content":""},{"type":"add","content":"  ### Articles faisant référence à l'article"},{"type":"add","content":"  "},{"type":"add","content":""},{"type":"add","content":""},{"type":"add","content":"Décret n° 2016-1922 du 28 décembre 2016 relatif à la publication en ligne des documents administratifs - article 2 ENTIEREMENT_MODIF MODIFIE source"},{"type":"add","content":""},{"type":"add","content":""},{"type":"add","content":"  "},{"type":"add","content":"  ### Textes faisant référence à l'article"},{"type":"add","content":"  "},{"type":"add","content":""},{"type":"add","content":""},{"type":"add","content":"Décret n° 2016-308 du 17 mars 2016 relatif à la réutilisation des informations publiques et modifiant le code des relations entre le public et l'administration (dispositions réglementaires) CITATION cible"},{"type":"add","content":""},{"type":"add","content":""},{"type":"add","content":"Décret n° 2016-1617 du 29 novembre 2016 relatif aux catégories d'informations publiques de l'Etat et de ses établissements publics administratifs susceptibles d'être soumises au paiement d'une redevance de réutilisation CITATION cible"},{"type":"add","content":""},{"type":"add","content":""},{"type":"add","content":"Décret n° 2016-1922 du 28 décembre 2016 relatif à la publication en ligne des documents administratifs CITATION cible"},{"type":"add","content":""},{"type":"add","content":""},{"type":"add","content":"Décret n° 2015-1342 du 23 octobre 2015 relatif aux dispositions réglementaires du code des relations entre le public et l'administration (Décrets en Conseil d'Etat et en conseil des ministres, décrets en Conseil d'Etat et décrets) CITATION cible"},{"type":"add","content":""},{"type":"add","content":""},{"type":"add","content":"  "},{"type":"add","content":"  ### Références faites par l'article"},{"type":"add","content":"  "},{"type":"add","content":""},{"type":"add","content":""},{"type":"add","content":"2015-10-23 CITATION source Décret n° 2015-1342 du 23 octobre 2015 relatif aux dispositions réglementaires du code des relations entre le public et l'administration (Décrets en Conseil d'Etat et en conseil des ministres, décrets en Conseil d'Etat et décrets)"},{"type":"add","content":""},{"type":"add","content":""},{"type":"add","content":"CODIFICATION source Décret n° 2015-1342 du 23 octobre 2015 relatif aux dispositions réglementaires du code des relations entre le public et l'administration (Décrets en Conseil d'Etat et en conseil des ministres, décrets en Conseil d'Etat et décrets)"},{"type":"add","content":""},{"type":"add","content":""},{"type":"add","content":"2016-03-17 CITATION source Décret n° 2016-308 du 17 mars 2016 relatif à la réutilisation des informations publiques et modifiant le code des relations entre le public et l'administration (dispositions réglementaires)"},{"type":"add","content":""},{"type":"add","content":""},{"type":"add","content":"2016-11-29 CITATION source Décret n° 2016-1617 du 29 novembre 2016 relatif aux catégories d'informations publiques de l'Etat et de ses établissements publics administratifs susceptibles d'être soumises au paiement d'une redevance de réutilisation"},{"type":"add","content":""},{"type":"add","content":""},{"type":"add","content":"2016-12-28 CITATION source Décret n° 2016-1922 du 28 décembre 2016 relatif à la publication en ligne des documents administratifs"},{"type":"add","content":""},{"type":"add","content":""},{"type":"add","content":"2016-12-28 MODIFIE cible Décret n° 2016-1922 du 28 décembre 2016 relatif à la publication en ligne des documents administratifs - article 2 ENTIEREMENT_MODIF"},{"type":"add","content":""},{"type":"add","content":""},{"type":"add","content":""},{"type":"add","content":""},{"type":"add","content":""},{"type":"add","content":"Autres formats"},{"type":"add","content":""},{"type":"add","content":"* [JSON dans git](https://git.tricoteuses.fr/dila/donnees_juridiques/src/branch/main/LEGI/ARTI/00/00/33/74/81/LEGIARTI000033748148.json)"},{"type":"add","content":"* [Références JSON dans git](https://git.tricoteuses.fr/dila/references_donnees_juridiques/src/branch/main/LEGI/ARTI/00/00/33/74/81/LEGIARTI000033748148.json)"},{"type":"add","content":"* [Markdown dans git](https://git.tricoteuses.fr/dila/textes_juridiques/src/branch/main/LEGI/ARTI/00/00/33/74/81/LEGIARTI000033748148.md)"},{"type":"add","content":"* [Markdown chronologique dans git](https://git.tricoteuses.fr/codes/code_des_relations_entre_le_public_et_l_administration/src/branch/main/livre_v/titre_vi/chapitre_ii/section_2/sous-section_3/article_d562-11.md)"},{"type":"add","content":"* [Légifrance](https://www.legifrance.gouv.fr/codes/article_lc/LEGIARTI000033748148)"},{"type":"add","content":""}],"status":"added"},{"filename":"livre_v/titre_vii/chapitre_iv/section_1/README.md","articleName":"Sommaire - Section 1","additions":1,"deletions":0,"diff":[{"type":"add","content":"- [Article D574-4](article_d574-4.md)"}],"status":"modified"},{"filename":"livre_v/titre_vii/chapitre_iv/section_1/article_d574-4.md","articleName":"Article D574-4","additions":125,"deletions":0,"diff":[{"type":"add","content":"---"},{"type":"add","content":"---"},{"type":"add","content":""},{"type":"add","content":"# Article D574-4"},{"type":"add","content":""},{"type":"add","content":"Les dispositions du livre III mentionnées dans la colonne de gauche du tableau ci-après sont applicables dans les îles Wallis et Futuna entre le public, d'une part, et l'Etat, ses établissements publics et les autres organismes et personnes de droit public et de droit privé chargés par l'Etat d'une mission de service public administratif et, le cas échéant, industriel et commercial, d'autre part, dans leur rédaction indiquée dans la colonne de droite du même tableau."},{"type":"add","content":""},{"type":"add","content":""},{"type":"add","content":""},{"type":"add","content":""},{"type":"add","content":""},{"type":"add","content":""},{"type":"add","content":"DISPOSITIONS APPLICABLES"},{"type":"add","content":"DANS LEUR RÉDACTION"},{"type":"add","content":""},{"type":"add","content":""},{"type":"add","content":""},{"type":"add","content":"D. 312-1-1-1 et D. 312-1-4"},{"type":"add","content":""},{"type":"add","content":""},{"type":"add","content":"Résultant du décret n° 2016-1922"},{"type":"add","content":""},{"type":"add","content":""},{"type":"add","content":""},{"type":"add","content":""},{"type":"add","content":"D. 324-5-1"},{"type":"add","content":""},{"type":"add","content":""},{"type":"add","content":"Résultant du décret n° 2016-1617"},{"type":"add","content":""},{"type":"add","content":""},{"type":"add","content":""},{"type":"add","content":""},{"type":"add","content":""},{"type":"add","content":""},{"type":"add","content":"D. 341-10"},{"type":"add","content":""},{"type":"add","content":""},{"type":"add","content":""},{"type":"add","content":""},{"type":"add","content":""},{"type":"add","content":"Résultant du décret n° 2016-308"},{"type":"add","content":""},{"type":"add","content":""},{"type":"add","content":""},{"type":"add","content":""},{"type":"add","content":""},{"type":"add","content":""},{"type":"add","content":""},{"type":"add","content":"D. 341-11 à D. 341-15"},{"type":"add","content":""},{"type":"add","content":""},{"type":"add","content":""},{"type":"add","content":""},{"type":"add","content":""},{"type":"add","content":"            Résultant du décret n° 2015-1342"},{"type":"add","content":""},{"type":"add","content":""},{"type":"add","content":""},{"type":"add","content":""},{"type":"add","content":""},{"type":"add","content":""},{"type":"add","content":""},{"type":"add","content":""},{"type":"add","content":""},{"type":"add","content":"Références"},{"type":"add","content":""},{"type":"add","content":"  ### Articles faisant référence à l'article"},{"type":"add","content":"  "},{"type":"add","content":""},{"type":"add","content":""},{"type":"add","content":"Décret n° 2016-1922 du 28 décembre 2016 relatif à la publication en ligne des documents administratifs - article 2 ENTIEREMENT_MODIF MODIFIE source"},{"type":"add","content":""},{"type":"add","content":""},{"type":"add","content":"  "},{"type":"add","content":"  ### Textes faisant référence à l'article"},{"type":"add","content":"  "},{"type":"add","content":""},{"type":"add","content":""},{"type":"add","content":"Décret n° 2016-308 du 17 mars 2016 relatif à la réutilisation des informations publiques et modifiant le code des relations entre le public et l'administration (dispositions réglementaires) CITATION cible"},{"type":"add","content":""},{"type":"add","content":""},{"type":"add","content":"Décret n° 2016-1617 du 29 novembre 2016 relatif aux catégories d'informations publiques de l'Etat et de ses établissements publics administratifs susceptibles d'être soumises au paiement d'une redevance de réutilisation CITATION cible"},{"type":"add","content":""},{"type":"add","content":""},{"type":"add","content":"Décret n° 2016-1922 du 28 décembre 2016 relatif à la publication en ligne des documents administratifs CITATION cible"},{"type":"add","content":""},{"type":"add","content":""},{"type":"add","content":"Décret n° 2015-1342 du 23 octobre 2015 relatif aux dispositions réglementaires du code des relations entre le public et l'administration (Décrets en Conseil d'Etat et en conseil des ministres, décrets en Conseil d'Etat et décrets) CITATION cible"},{"type":"add","content":""},{"type":"add","content":""},{"type":"add","content":"  "},{"type":"add","content":"  ### Références faites par l'article"},{"type":"add","content":"  "},{"type":"add","content":""},{"type":"add","content":""},{"type":"add","content":"2015-10-23 CITATION source Décret n° 2015-1342 du 23 octobre 2015 relatif aux dispositions réglementaires du code des relations entre le public et l'administration (Décrets en Conseil d'Etat et en conseil des ministres, décrets en Conseil d'Etat et décrets)"},{"type":"add","content":""},{"type":"add","content":""},{"type":"add","content":"CODIFICATION source Décret n° 2015-1342 du 23 octobre 2015 relatif aux dispositions réglementaires du code des relations entre le public et l'administration (Décrets en Conseil d'Etat et en conseil des ministres, décrets en Conseil d'Etat et décrets)"},{"type":"add","content":""},{"type":"add","content":""},{"type":"add","content":"2016-03-17 CITATION source Décret n° 2016-308 du 17 mars 2016 relatif à la réutilisation des informations publiques et modifiant le code des relations entre le public et l'administration (dispositions réglementaires)"},{"type":"add","content":""},{"type":"add","content":""},{"type":"add","content":"2016-11-29 CITATION source Décret n° 2016-1617 du 29 novembre 2016 relatif aux catégories d'informations publiques de l'Etat et de ses établissements publics administratifs susceptibles d'être soumises au paiement d'une redevance de réutilisation"},{"type":"add","content":""},{"type":"add","content":""},{"type":"add","content":"2016-12-28 CITATION source Décret n° 2016-1922 du 28 décembre 2016 relatif à la publication en ligne des documents administratifs"},{"type":"add","content":""},{"type":"add","content":""},{"type":"add","content":"2016-12-28 MODIFIE cible Décret n° 2016-1922 du 28 décembre 2016 relatif à la publication en ligne des documents administratifs - article 2 ENTIEREMENT_MODIF"},{"type":"add","content":""},{"type":"add","content":""},{"type":"add","content":""},{"type":"add","content":""},{"type":"add","content":""},{"type":"add","content":"Autres formats"},{"type":"add","content":""},{"type":"add","content":"* [JSON dans git](https://git.tricoteuses.fr/dila/donnees_juridiques/src/branch/main/LEGI/ARTI/00/00/33/74/81/LEGIARTI000033748143.json)"},{"type":"add","content":"* [Références JSON dans git](https://git.tricoteuses.fr/dila/references_donnees_juridiques/src/branch/main/LEGI/ARTI/00/00/33/74/81/LEGIARTI000033748143.json)"},{"type":"add","content":"* [Markdown dans git](https://git.tricoteuses.fr/dila/textes_juridiques/src/branch/main/LEGI/ARTI/00/00/33/74/81/LEGIARTI000033748143.md)"},{"type":"add","content":"* [Markdown chronologique dans git](https://git.tricoteuses.fr/codes/code_des_relations_entre_le_public_et_l_administration/src/branch/main/livre_v/titre_vii/chapitre_iv/section_1/article_d574-4.md)"},{"type":"add","content":"* [Légifrance](https://www.legifrance.gouv.fr/codes/article_lc/LEGIARTI000033748143)"},{"type":"add","content":""}],"status":"added"}],"stats":{"additions":475,"deletions":0,"filesChanged":9}}